{
  "date": "2024-07-15",
  "data": [
    {
      "lastYearRptDt": "7/17/2023",
      "lastYearEPS": "$0.80",
      "time": "time-not-supplied",
      "symbol": "HDB",
      "name": "HDFC Bank Limited",
      "marketCap": "$154,897,052,505",
      "fiscalQuarterEnding": "Jun/2024",
      "epsForecast": "$0.49",
      "noOfEsts": "1"
    },
    {
      "lastYearRptDt": "7/19/2023",
      "lastYearEPS": "$3.08",
      "time": "time-pre-market",
      "symbol": "GS",
      "name": "Goldman Sachs Group, Inc. (The)",
      "marketCap": "$147,504,477,432",
      "fiscalQuarterEnding": "Jun/2024",
      "epsForecast": "$8.88",
      "noOfEsts": "7"
    },
    {
      "lastYearRptDt": "7/17/2023",
      "lastYearEPS": "$0.66",
      "time": "time-not-supplied",
      "symbol": "ELS",
      "name": "Equity Lifestyle Properties, Inc.",
      "marketCap": "$11,728,724,698",
      "fiscalQuarterEnding": "Jun/2024",
      "epsForecast": "$0.65",
      "noOfEsts": "3"
    },
    {
      "lastYearRptDt": "7/17/2023",
      "lastYearEPS": "$0.77",
      "time": "time-not-supplied",
      "symbol": "FBK",
      "name": "FB Financial Corporation",
      "marketCap": "$1,724,916,815",
      "fiscalQuarterEnding": "Jun/2024",
      "epsForecast": "$0.75",
      "noOfEsts": "4"
    },
    {
      "lastYearRptDt": "7/17/2023",
      "lastYearEPS": "$0.35",
      "time": "time-not-supplied",
      "symbol": "CFB",
      "name": "CrossFirst Bankshares, Inc.",
      "marketCap": "$642,287,490",
      "fiscalQuarterEnding": "Jun/2024",
      "epsForecast": "$0.34",
      "noOfEsts": "3"
    },
    {
      "lastYearRptDt": "7/17/2023",
      "lastYearEPS": "$0.63",
      "time": "time-not-supplied",
      "symbol": "GNTY",
      "name": "Guaranty Bancshares, Inc.",
      "marketCap": "$338,486,393",
      "fiscalQuarterEnding": "Jun/2024",
      "epsForecast": "$0.55",
      "noOfEsts": "1"
    },
    {
      "lastYearRptDt": "7/17/2023",
      "lastYearEPS": "$1.21",
      "time": "time-not-supplied",
      "symbol": "HBCP",
      "name": "Home Bancorp, Inc.",
      "marketCap": "$304,731,241",
      "fiscalQuarterEnding": "Jun/2024",
      "epsForecast": "$0.98",
      "noOfEsts": "2"
    },
    {
      "lastYearRptDt": "N/A",
      "lastYearEPS": "$1.05",
      "time": "time-not-supplied",
      "symbol": "VABK",
      "name": "Virginia National Bankshares Corporation",
      "marketCap": "$163,007,179",
      "fiscalQuarterEnding": "Jun/2024",
      "epsForecast": "",
      "noOfEsts": "N/A"
    },
    {
      "lastYearRptDt": "7/17/2023",
      "lastYearEPS": "($0.04)",
      "time": "time-not-supplied",
      "symbol": "AMLI",
      "name": "American Lithium Corp.",
      "marketCap": "$127,881,474",
      "fiscalQuarterEnding": "May/2024",
      "epsForecast": "",
      "noOfEsts": "N/A"
    },
    {
      "lastYearRptDt": "N/A",
      "lastYearEPS": "N/A",
      "time": "time-not-supplied",
      "symbol": "SATL",
      "name": "Satellogic Inc.",
      "marketCap": "$97,528,303",
      "fiscalQuarterEnding": "Mar/2024",
      "epsForecast": "",
      "noOfEsts": "N/A"
    },
    {
      "lastYearRptDt": "N/A",
      "lastYearEPS": "N/A",
      "time": "time-not-supplied",
      "symbol": "GRDI",
      "name": "GRIID Infrastructure Inc.",
      "marketCap": "$39,970,509",
      "fiscalQuarterEnding": "Mar/2024",
      "epsForecast": "",
      "noOfEsts": "N/A"
    },
    {
      "lastYearRptDt": "N/A",
      "lastYearEPS": "($16.79)",
      "time": "time-not-supplied",
      "symbol": "PIXY",
      "name": "ShiftPixy, Inc.",
      "marketCap": "$16,078,532",
      "fiscalQuarterEnding": "May/2024",
      "epsForecast": "",
      "noOfEsts": "N/A"
    },
    {
      "lastYearRptDt": "N/A",
      "lastYearEPS": "($0.10)",
      "time": "time-not-supplied",
      "symbol": "NVOS",
      "name": "Novo Integrated Sciences, Inc.",
      "marketCap": "$15,603,748",
      "fiscalQuarterEnding": "May/2024",
      "epsForecast": "",
      "noOfEsts": "N/A"
    },
    {
      "lastYearRptDt": "N/A",
      "lastYearEPS": "N/A",
      "time": "time-not-supplied",
      "symbol": "CLEU",
      "name": "China Liberal Education Holdings Limited",
      "marketCap": "$9,258,356",
      "fiscalQuarterEnding": "Mar/2024",
      "epsForecast": "",
      "noOfEsts": "N/A"
    },
    {
      "lastYearRptDt": "N/A",
      "lastYearEPS": "N/A",
      "time": "time-not-supplied",
      "symbol": "PAPL",
      "name": "Pineapple Financial Inc.",
      "marketCap": "$6,965,794",
      "fiscalQuarterEnding": "May/2024",
      "epsForecast": "",
      "noOfEsts": "N/A"
    }
  ]
}