{
  "date": "2025-08-18",
  "data": [
    {
      "lastYearRptDt": "8/19/2024",
      "lastYearEPS": "$0.43",
      "time": "time-not-supplied",
      "symbol": "PANW",
      "name": "Palo Alto Networks, Inc.",
      "marketCap": "$130,546,104,000",
      "fiscalQuarterEnding": "Jul/2025",
      "epsForecast": "$0.50",
      "noOfEsts": "15"
    },
    {
      "lastYearRptDt": "8/19/2024",
      "lastYearEPS": "$2.22",
      "time": "time-not-supplied",
      "symbol": "FN",
      "name": "Fabrinet",
      "marketCap": "$11,141,541,861",
      "fiscalQuarterEnding": "Jun/2025",
      "epsForecast": "$2.40",
      "noOfEsts": "3"
    },
    {
      "lastYearRptDt": "N/A",
      "lastYearEPS": "N/A",
      "time": "time-not-supplied",
      "symbol": "SNRE",
      "name": "Sunrise Communications AG",
      "marketCap": "$5,418,715,219",
      "fiscalQuarterEnding": "Jun/2025",
      "epsForecast": "",
      "noOfEsts": "N/A"
    },
    {
      "lastYearRptDt": "8/19/2024",
      "lastYearEPS": "($0.05)",
      "time": "time-not-supplied",
      "symbol": "HSAI",
      "name": "Hesai Group",
      "marketCap": "$2,881,171,692",
      "fiscalQuarterEnding": "Jun/2025",
      "epsForecast": "",
      "noOfEsts": "N/A"
    },
    {
      "lastYearRptDt": "8/19/2024",
      "lastYearEPS": "$3.08",
      "time": "time-not-supplied",
      "symbol": "ZIM",
      "name": "ZIM Integrated Shipping Services Ltd.",
      "marketCap": "$1,864,682,255",
      "fiscalQuarterEnding": "Jun/2025",
      "epsForecast": "$0.92",
      "noOfEsts": "3"
    },
    {
      "lastYearRptDt": "8/19/2024",
      "lastYearEPS": "($0.01)",
      "time": "time-not-supplied",
      "symbol": "BTBT",
      "name": "Bit Digital, Inc.",
      "marketCap": "$797,878,545",
      "fiscalQuarterEnding": "Jun/2025",
      "epsForecast": "($0.02)",
      "noOfEsts": "4"
    },
    {
      "lastYearRptDt": "8/19/2024",
      "lastYearEPS": "($0.24)",
      "time": "time-not-supplied",
      "symbol": "ASPI",
      "name": "ASP Isotopes Inc.",
      "marketCap": "$787,398,723",
      "fiscalQuarterEnding": "Jun/2025",
      "epsForecast": "",
      "noOfEsts": "N/A"
    },
    {
      "lastYearRptDt": "8/19/2024",
      "lastYearEPS": "($0.10)",
      "time": "time-not-supplied",
      "symbol": "API",
      "name": "Agora, Inc.",
      "marketCap": "$373,107,857",
      "fiscalQuarterEnding": "Jun/2025",
      "epsForecast": "",
      "noOfEsts": "N/A"
    },
    {
      "lastYearRptDt": "8/19/2024",
      "lastYearEPS": "($0.09)",
      "time": "time-not-supplied",
      "symbol": "LZM",
      "name": "Lifezone Metals Limited",
      "marketCap": "$341,972,540",
      "fiscalQuarterEnding": "Jun/2025",
      "epsForecast": "($0.12)",
      "noOfEsts": "1"
    },
    {
      "lastYearRptDt": "N/A",
      "lastYearEPS": "($0.09)",
      "time": "time-not-supplied",
      "symbol": "MLP",
      "name": "Maui Land & Pineapple Company, Inc.",
      "marketCap": "$335,805,569",
      "fiscalQuarterEnding": "Jun/2025",
      "epsForecast": "",
      "noOfEsts": "N/A"
    },
    {
      "lastYearRptDt": "N/A",
      "lastYearEPS": "($0.17)",
      "time": "time-not-supplied",
      "symbol": "INV",
      "name": "Innventure, Inc.",
      "marketCap": "$265,831,851",
      "fiscalQuarterEnding": "Jun/2025",
      "epsForecast": "($0.17)",
      "noOfEsts": "N/A"
    },
    {
      "lastYearRptDt": "N/A",
      "lastYearEPS": "($0.24)",
      "time": "time-not-supplied",
      "symbol": "AREN",
      "name": "The Arena Group Holdings, Inc.",
      "marketCap": "$249,219,388",
      "fiscalQuarterEnding": "Jun/2025",
      "epsForecast": "",
      "noOfEsts": "N/A"
    },
    {
      "lastYearRptDt": "8/19/2024",
      "lastYearEPS": "($0.32)",
      "time": "time-not-supplied",
      "symbol": "ELDN",
      "name": "Eledon Pharmaceuticals, Inc.",
      "marketCap": "$221,562,568",
      "fiscalQuarterEnding": "Jun/2025",
      "epsForecast": "($0.23)",
      "noOfEsts": "4"
    },
    {
      "lastYearRptDt": "8/19/2024",
      "lastYearEPS": "$0.75",
      "time": "time-not-supplied",
      "symbol": "FLXS",
      "name": "Flexsteel Industries, Inc.",
      "marketCap": "$195,479,489",
      "fiscalQuarterEnding": "Jun/2025",
      "epsForecast": "$0.84",
      "noOfEsts": "1"
    },
    {
      "lastYearRptDt": "8/19/2024",
      "lastYearEPS": "($0.04)",
      "time": "time-not-supplied",
      "symbol": "BTCS",
      "name": "BTCS Inc.",
      "marketCap": "$138,596,712",
      "fiscalQuarterEnding": "Jun/2025",
      "epsForecast": "($0.07)",
      "noOfEsts": "1"
    },
    {
      "lastYearRptDt": "N/A",
      "lastYearEPS": "($0.13)",
      "time": "time-not-supplied",
      "symbol": "ZEO",
      "name": "Zeo Energy Corporation",
      "marketCap": "$122,769,064",
      "fiscalQuarterEnding": "Jun/2025",
      "epsForecast": "",
      "noOfEsts": "N/A"
    },
    {
      "lastYearRptDt": "8/19/2024",
      "lastYearEPS": "($0.11)",
      "time": "time-not-supplied",
      "symbol": "CRGO",
      "name": "Freightos Limited",
      "marketCap": "$120,603,001",
      "fiscalQuarterEnding": "Jun/2025",
      "epsForecast": "($0.09)",
      "noOfEsts": "1"
    },
    {
      "lastYearRptDt": "8/19/2024",
      "lastYearEPS": "($0.09)",
      "time": "time-not-supplied",
      "symbol": "AREC",
      "name": "American Resources Corporation",
      "marketCap": "$111,070,849",
      "fiscalQuarterEnding": "Jun/2025",
      "epsForecast": "$0",
      "noOfEsts": "1"
    },
    {
      "lastYearRptDt": "N/A",
      "lastYearEPS": "($0.09)",
      "time": "time-not-supplied",
      "symbol": "AGAE",
      "name": "Allied Gaming & Entertainment Inc.",
      "marketCap": "$69,954,743",
      "fiscalQuarterEnding": "Jun/2025",
      "epsForecast": "",
      "noOfEsts": "N/A"
    },
    {
      "lastYearRptDt": "8/19/2024",
      "lastYearEPS": "($0.50)",
      "time": "time-not-supplied",
      "symbol": "FLNT",
      "name": "Fluent, Inc.",
      "marketCap": "$46,241,798",
      "fiscalQuarterEnding": "Jun/2025",
      "epsForecast": "($0.26)",
      "noOfEsts": "1"
    },
    {
      "lastYearRptDt": "N/A",
      "lastYearEPS": "($0.03)",
      "time": "time-not-supplied",
      "symbol": "KLTO",
      "name": "Klotho Neurosciences, Inc.",
      "marketCap": "$41,917,762",
      "fiscalQuarterEnding": "Jun/2025",
      "epsForecast": "",
      "noOfEsts": "N/A"
    },
    {
      "lastYearRptDt": "N/A",
      "lastYearEPS": "($0.58)",
      "time": "time-not-supplied",
      "symbol": "AIFF",
      "name": "Firefly Neuroscience, Inc. ",
      "marketCap": "$38,969,127",
      "fiscalQuarterEnding": "Jun/2025",
      "epsForecast": "",
      "noOfEsts": "N/A"
    },
    {
      "lastYearRptDt": "N/A",
      "lastYearEPS": "($0.99)",
      "time": "time-not-supplied",
      "symbol": "SIDU",
      "name": "Sidus Space, Inc.",
      "marketCap": "$36,792,011",
      "fiscalQuarterEnding": "Jun/2025",
      "epsForecast": "",
      "noOfEsts": "N/A"
    },
    {
      "lastYearRptDt": "N/A",
      "lastYearEPS": "N/A",
      "time": "time-not-supplied",
      "symbol": "AKTX",
      "name": "Akari Therapeutics Plc",
      "marketCap": "$36,359,298",
      "fiscalQuarterEnding": "Jun/2025",
      "epsForecast": "",
      "noOfEsts": "N/A"
    },
    {
      "lastYearRptDt": "N/A",
      "lastYearEPS": "($1.47)",
      "time": "time-not-supplied",
      "symbol": "SEGG",
      "name": "Lottery.com, Inc.",
      "marketCap": "$30,972,070",
      "fiscalQuarterEnding": "Jun/2025",
      "epsForecast": "",
      "noOfEsts": "N/A"
    },
    {
      "lastYearRptDt": "N/A",
      "lastYearEPS": "N/A",
      "time": "time-not-supplied",
      "symbol": "APUS",
      "name": "Apimeds Pharmaceuticals US, Inc.",
      "marketCap": "$20,489,490",
      "fiscalQuarterEnding": "Jun/2025",
      "epsForecast": "",
      "noOfEsts": "N/A"
    },
    {
      "lastYearRptDt": "N/A",
      "lastYearEPS": "($0.14)",
      "time": "time-not-supplied",
      "symbol": "NXGL",
      "name": "NexGel, Inc",
      "marketCap": "$18,523,980",
      "fiscalQuarterEnding": "Jun/2025",
      "epsForecast": "",
      "noOfEsts": "N/A"
    },
    {
      "lastYearRptDt": "N/A",
      "lastYearEPS": "($0.02)",
      "time": "time-not-supplied",
      "symbol": "CETY",
      "name": "Clean Energy Technologies, Inc.",
      "marketCap": "$13,742,899",
      "fiscalQuarterEnding": "Jun/2025",
      "epsForecast": "",
      "noOfEsts": "N/A"
    },
    {
      "lastYearRptDt": "N/A",
      "lastYearEPS": "($0.48)",
      "time": "time-not-supplied",
      "symbol": "REBN",
      "name": "Reborn Coffee, Inc.",
      "marketCap": "$13,470,397",
      "fiscalQuarterEnding": "Jun/2025",
      "epsForecast": "",
      "noOfEsts": "N/A"
    },
    {
      "lastYearRptDt": "N/A",
      "lastYearEPS": "($0.90)",
      "time": "time-not-supplied",
      "symbol": "FTFT",
      "name": "Future FinTech Group Inc.",
      "marketCap": "$13,005,754",
      "fiscalQuarterEnding": "Jun/2025",
      "epsForecast": "",
      "noOfEsts": "N/A"
    },
    {
      "lastYearRptDt": "8/19/2024",
      "lastYearEPS": "($0.55)",
      "time": "time-not-supplied",
      "symbol": "MIGI",
      "name": "Mawson Infrastructure Group Inc.",
      "marketCap": "$11,717,792",
      "fiscalQuarterEnding": "Jun/2025",
      "epsForecast": "($0.12)",
      "noOfEsts": "1"
    },
    {
      "lastYearRptDt": "N/A",
      "lastYearEPS": "($0.82)",
      "time": "time-not-supplied",
      "symbol": "YOSH",
      "name": "Yoshiharu Global Co.",
      "marketCap": "$11,313,613",
      "fiscalQuarterEnding": "Jun/2025",
      "epsForecast": "",
      "noOfEsts": "N/A"
    },
    {
      "lastYearRptDt": "8/19/2024",
      "lastYearEPS": "($0.03)",
      "time": "time-not-supplied",
      "symbol": "ECDA",
      "name": "ECD Automotive Design, Inc.",
      "marketCap": "$9,748,750",
      "fiscalQuarterEnding": "Jun/2025",
      "epsForecast": "",
      "noOfEsts": "N/A"
    },
    {
      "lastYearRptDt": "N/A",
      "lastYearEPS": "($0.28)",
      "time": "time-not-supplied",
      "symbol": "HCTI",
      "name": "Healthcare Triangle, Inc.",
      "marketCap": "$7,883,000",
      "fiscalQuarterEnding": "Jun/2025",
      "epsForecast": "",
      "noOfEsts": "N/A"
    },
    {
      "lastYearRptDt": "N/A",
      "lastYearEPS": "($0.08)",
      "time": "time-not-supplied",
      "symbol": "SGN",
      "name": "Signing Day Sports, Inc.",
      "marketCap": "$7,643,882",
      "fiscalQuarterEnding": "Jun/2025",
      "epsForecast": "",
      "noOfEsts": "N/A"
    },
    {
      "lastYearRptDt": "N/A",
      "lastYearEPS": "($0.19)",
      "time": "time-not-supplied",
      "symbol": "UUU",
      "name": "Universal Security Instruments, Inc.",
      "marketCap": "$7,609,398",
      "fiscalQuarterEnding": "Jun/2025",
      "epsForecast": "",
      "noOfEsts": "N/A"
    },
    {
      "lastYearRptDt": "N/A",
      "lastYearEPS": "($99.99)",
      "time": "time-not-supplied",
      "symbol": "SUNE",
      "name": "SUNation Energy, Inc.",
      "marketCap": "$6,200,037",
      "fiscalQuarterEnding": "Jun/2025",
      "epsForecast": "",
      "noOfEsts": "N/A"
    },
    {
      "lastYearRptDt": "8/19/2024",
      "lastYearEPS": "($0.73)",
      "time": "time-not-supplied",
      "symbol": "SOPA",
      "name": "Society Pass Incorporated",
      "marketCap": "$6,163,605",
      "fiscalQuarterEnding": "Jun/2025",
      "epsForecast": "($0.24)",
      "noOfEsts": "1"
    },
    {
      "lastYearRptDt": "8/19/2024",
      "lastYearEPS": "($99.99)",
      "time": "time-not-supplied",
      "symbol": "RIME",
      "name": "Algorhythm Holdings, Inc.",
      "marketCap": "$5,985,936",
      "fiscalQuarterEnding": "Jun/2025",
      "epsForecast": "",
      "noOfEsts": "N/A"
    },
    {
      "lastYearRptDt": "8/19/2024",
      "lastYearEPS": "($99.99)",
      "time": "time-not-supplied",
      "symbol": "WINT",
      "name": "Windtree Therapeutics, Inc.",
      "marketCap": "$4,356,934",
      "fiscalQuarterEnding": "Jun/2025",
      "epsForecast": "",
      "noOfEsts": "N/A"
    },
    {
      "lastYearRptDt": "N/A",
      "lastYearEPS": "($2.85)",
      "time": "time-not-supplied",
      "symbol": "ALBT",
      "name": "Avalon GloboCare Corp.",
      "marketCap": "$4,090,977",
      "fiscalQuarterEnding": "Jun/2025",
      "epsForecast": "",
      "noOfEsts": "N/A"
    },
    {
      "lastYearRptDt": "N/A",
      "lastYearEPS": "($99.99)",
      "time": "time-not-supplied",
      "symbol": "ADTX",
      "name": "Aditxt, Inc.",
      "marketCap": "$2,459,260",
      "fiscalQuarterEnding": "Jun/2025",
      "epsForecast": "",
      "noOfEsts": "N/A"
    },
    {
      "lastYearRptDt": "N/A",
      "lastYearEPS": "($0.76)",
      "time": "time-not-supplied",
      "symbol": "IMG",
      "name": "CIMG Inc.",
      "marketCap": "$1,359,905",
      "fiscalQuarterEnding": "Jun/2025",
      "epsForecast": "",
      "noOfEsts": "N/A"
    },
    {
      "lastYearRptDt": "N/A",
      "lastYearEPS": "($1.81)",
      "time": "time-not-supplied",
      "symbol": "TNFA",
      "name": "TNF Pharmaceuticals, Inc. ",
      "marketCap": "$1,241,108",
      "fiscalQuarterEnding": "Jun/2025",
      "epsForecast": "",
      "noOfEsts": "N/A"
    },
    {
      "lastYearRptDt": "N/A",
      "lastYearEPS": "($2.40)",
      "time": "time-not-supplied",
      "symbol": "FOXO",
      "name": "FOXO Technologies Inc.",
      "marketCap": "$696,656",
      "fiscalQuarterEnding": "Jun/2025",
      "epsForecast": "",
      "noOfEsts": "N/A"
    }
  ]
}