{
  "date": "2025-06-09",
  "data": [
    {
      "lastYearRptDt": "6/11/2024",
      "lastYearEPS": "$2.34",
      "time": "time-after-hours",
      "symbol": "CASY",
      "name": "Caseys General Stores, Inc.",
      "marketCap": "$16,249,215,191",
      "fiscalQuarterEnding": "Apr/2025",
      "epsForecast": "$1.93",
      "noOfEsts": "6"
    },
    {
      "lastYearRptDt": "4/17/2024",
      "lastYearEPS": "($0.26)",
      "time": "time-pre-market",
      "symbol": "VFS",
      "name": "VinFast Auto Ltd.",
      "marketCap": "$7,601,141,197",
      "fiscalQuarterEnding": "Mar/2025",
      "epsForecast": "($0.26)",
      "noOfEsts": "1"
    },
    {
      "lastYearRptDt": "6/10/2024",
      "lastYearEPS": "$0.50",
      "time": "time-after-hours",
      "symbol": "CVGW",
      "name": "Calavo Growers, Inc.",
      "marketCap": "$491,395,768",
      "fiscalQuarterEnding": "Apr/2025",
      "epsForecast": "",
      "noOfEsts": "N/A"
    },
    {
      "lastYearRptDt": "6/07/2024",
      "lastYearEPS": "$0.12",
      "time": "time-pre-market",
      "symbol": "GHM",
      "name": "Graham Corporation",
      "marketCap": "$429,902,806",
      "fiscalQuarterEnding": "Mar/2025",
      "epsForecast": "$0.26",
      "noOfEsts": "1"
    },
    {
      "lastYearRptDt": "N/A",
      "lastYearEPS": "N/A",
      "time": "time-after-hours",
      "symbol": "AII",
      "name": "American Integrity Insurance Group, Inc.",
      "marketCap": "$324,470,890",
      "fiscalQuarterEnding": "Mar/2025",
      "epsForecast": "",
      "noOfEsts": "1"
    },
    {
      "lastYearRptDt": "6/06/2024",
      "lastYearEPS": "$0.40",
      "time": "time-after-hours",
      "symbol": "LMNR",
      "name": "Limoneira Co",
      "marketCap": "$284,933,219",
      "fiscalQuarterEnding": "Apr/2025",
      "epsForecast": "$0",
      "noOfEsts": "1"
    },
    {
      "lastYearRptDt": "6/04/2024",
      "lastYearEPS": "$0.22",
      "time": "time-after-hours",
      "symbol": "LAKE",
      "name": "Lakeland Industries, Inc.",
      "marketCap": "$181,043,392",
      "fiscalQuarterEnding": "Apr/2025",
      "epsForecast": "$0.27",
      "noOfEsts": "1"
    },
    {
      "lastYearRptDt": "6/10/2024",
      "lastYearEPS": "($3.42)",
      "time": "time-after-hours",
      "symbol": "SKIL",
      "name": "Skillsoft Corp.",
      "marketCap": "$166,418,280",
      "fiscalQuarterEnding": "Apr/2025",
      "epsForecast": "($3.74)",
      "noOfEsts": "1"
    },
    {
      "lastYearRptDt": "N/A",
      "lastYearEPS": "($0.21)",
      "time": "time-not-supplied",
      "symbol": "OCC",
      "name": "Optical Cable Corporation",
      "marketCap": "$23,775,873",
      "fiscalQuarterEnding": "Apr/2025",
      "epsForecast": "",
      "noOfEsts": "1"
    },
    {
      "lastYearRptDt": "N/A",
      "lastYearEPS": "N/A",
      "time": "time-not-supplied",
      "symbol": "CHR",
      "name": "Cheer Holding, Inc. ",
      "marketCap": "$17,716,716",
      "fiscalQuarterEnding": "Mar/2025",
      "epsForecast": "",
      "noOfEsts": "1"
    },
    {
      "lastYearRptDt": "N/A",
      "lastYearEPS": "N/A",
      "time": "time-not-supplied",
      "symbol": "IINN",
      "name": "Inspira Technologies Oxy B.H.N. Ltd.",
      "marketCap": "$14,796,204",
      "fiscalQuarterEnding": "Mar/2025",
      "epsForecast": "",
      "noOfEsts": "N/A"
    }
  ]
}