{
  "date": "2025-07-18",
  "data": [
    {
      "lastYearRptDt": "7/19/2024",
      "lastYearEPS": "$3.49",
      "time": "time-not-supplied",
      "symbol": "AXP",
      "name": "American Express Company",
      "marketCap": "$207,668,552,845",
      "fiscalQuarterEnding": "Jun/2025",
      "epsForecast": "$3.86",
      "noOfEsts": "14"
    },
    {
      "lastYearRptDt": "7/20/2024",
      "lastYearEPS": "$0.78",
      "time": "time-not-supplied",
      "symbol": "HDB",
      "name": "HDFC Bank Limited",
      "marketCap": "$188,403,384,418",
      "fiscalQuarterEnding": "Jun/2025",
      "epsForecast": "$0.75",
      "noOfEsts": "1"
    },
    {
      "lastYearRptDt": "7/19/2024",
      "lastYearEPS": "$1.22",
      "time": "time-not-supplied",
      "symbol": "SCCO",
      "name": "Southern Copper Corporation",
      "marketCap": "$75,836,726,501",
      "fiscalQuarterEnding": "Jun/2025",
      "epsForecast": "$1.05",
      "noOfEsts": "2"
    },
    {
      "lastYearRptDt": "7/19/2024",
      "lastYearEPS": "$0.85",
      "time": "time-not-supplied",
      "symbol": "SLB",
      "name": "Schlumberger N.V.",
      "marketCap": "$48,761,795,296",
      "fiscalQuarterEnding": "Jun/2025",
      "epsForecast": "$0.75",
      "noOfEsts": "7"
    },
    {
      "lastYearRptDt": "7/19/2024",
      "lastYearEPS": "$0.04",
      "time": "time-not-supplied",
      "symbol": "WIT",
      "name": "Wipro Limited",
      "marketCap": "$31,206,965,426",
      "fiscalQuarterEnding": "Jun/2025",
      "epsForecast": "",
      "noOfEsts": "N/A"
    },
    {
      "lastYearRptDt": "7/19/2024",
      "lastYearEPS": "$0.30",
      "time": "time-not-supplied",
      "symbol": "HBAN",
      "name": "Huntington Bancshares Incorporated",
      "marketCap": "$22,915,646,798",
      "fiscalQuarterEnding": "Jun/2025",
      "epsForecast": "$0.35",
      "noOfEsts": "10"
    },
    {
      "lastYearRptDt": "7/19/2024",
      "lastYearEPS": "$1.55",
      "time": "time-not-supplied",
      "symbol": "KOF",
      "name": "Coca Cola Femsa S.A.B. de C.V.",
      "marketCap": "$19,756,226,573",
      "fiscalQuarterEnding": "Jun/2025",
      "epsForecast": "$1.57",
      "noOfEsts": "1"
    },
    {
      "lastYearRptDt": "7/19/2024",
      "lastYearEPS": "$0.52",
      "time": "time-pre-market",
      "symbol": "RF",
      "name": "Regions Financial Corporation",
      "marketCap": "$19,740,506,182",
      "fiscalQuarterEnding": "Jun/2025",
      "epsForecast": "$0.56",
      "noOfEsts": "11"
    },
    {
      "lastYearRptDt": "7/19/2024",
      "lastYearEPS": "$0.80",
      "time": "time-not-supplied",
      "symbol": "HAL",
      "name": "Halliburton Company",
      "marketCap": "$19,154,450,579",
      "fiscalQuarterEnding": "Jun/2025",
      "epsForecast": "$0.57",
      "noOfEsts": "11"
    },
    {
      "lastYearRptDt": "7/17/2024",
      "lastYearEPS": "$0.97",
      "time": "time-pre-market",
      "symbol": "ALLY",
      "name": "Ally Financial Inc.",
      "marketCap": "$11,316,315,911",
      "fiscalQuarterEnding": "Jun/2025",
      "epsForecast": "$0.76",
      "noOfEsts": "9"
    },
    {
      "lastYearRptDt": "7/19/2024",
      "lastYearEPS": "$1.87",
      "time": "time-pre-market",
      "symbol": "ALV",
      "name": "Autoliv, Inc.",
      "marketCap": "$8,526,759,148",
      "fiscalQuarterEnding": "Jun/2025",
      "epsForecast": "$2.06",
      "noOfEsts": "4"
    },
    {
      "lastYearRptDt": "7/19/2024",
      "lastYearEPS": "$1.53",
      "time": "time-pre-market",
      "symbol": "CMA",
      "name": "Comerica Incorporated",
      "marketCap": "$7,336,777,964",
      "fiscalQuarterEnding": "Jun/2025",
      "epsForecast": "$1.25",
      "noOfEsts": "9"
    },
    {
      "lastYearRptDt": "7/19/2024",
      "lastYearEPS": "$1.12",
      "time": "time-not-supplied",
      "symbol": "BMI",
      "name": "Badger Meter, Inc.",
      "marketCap": "$7,117,097,103",
      "fiscalQuarterEnding": "Jun/2025",
      "epsForecast": "$1.18",
      "noOfEsts": "4"
    },
    {
      "lastYearRptDt": "N/A",
      "lastYearEPS": "$1.30",
      "time": "time-not-supplied",
      "symbol": "RBCAA",
      "name": "Republic Bancorp, Inc.",
      "marketCap": "$1,338,817,250",
      "fiscalQuarterEnding": "Jun/2025",
      "epsForecast": "",
      "noOfEsts": "9"
    },
    {
      "lastYearRptDt": "N/A",
      "lastYearEPS": "$0.66",
      "time": "time-not-supplied",
      "symbol": "MCBS",
      "name": "MetroCity Bankshares, Inc.",
      "marketCap": "$682,792,535",
      "fiscalQuarterEnding": "Jun/2025",
      "epsForecast": "",
      "noOfEsts": "9"
    },
    {
      "lastYearRptDt": "7/19/2024",
      "lastYearEPS": "N/A",
      "time": "time-not-supplied",
      "symbol": "SIFY",
      "name": "Sify Technologies Limited",
      "marketCap": "$314,724,240",
      "fiscalQuarterEnding": "Jun/2025",
      "epsForecast": "($0.01)",
      "noOfEsts": "1"
    },
    {
      "lastYearRptDt": "N/A",
      "lastYearEPS": "$0.53",
      "time": "time-not-supplied",
      "symbol": "PKBK",
      "name": "Parke Bancorp, Inc.",
      "marketCap": "$225,615,398",
      "fiscalQuarterEnding": "Jun/2025",
      "epsForecast": "",
      "noOfEsts": "9"
    },
    {
      "lastYearRptDt": "N/A",
      "lastYearEPS": "$0.77",
      "time": "time-not-supplied",
      "symbol": "VABK",
      "name": "Virginia National Bankshares Corporation",
      "marketCap": "$200,635,539",
      "fiscalQuarterEnding": "Jun/2025",
      "epsForecast": "",
      "noOfEsts": "9"
    },
    {
      "lastYearRptDt": "N/A",
      "lastYearEPS": "$1.09",
      "time": "time-not-supplied",
      "symbol": "ACU",
      "name": "Acme United Corporation.",
      "marketCap": "$145,941,527",
      "fiscalQuarterEnding": "Jun/2025",
      "epsForecast": "",
      "noOfEsts": "9"
    },
    {
      "lastYearRptDt": "7/19/2024",
      "lastYearEPS": "$0.14",
      "time": "time-not-supplied",
      "symbol": "BCBP",
      "name": "BCB Bancorp, Inc. (NJ)",
      "marketCap": "$133,868,491",
      "fiscalQuarterEnding": "Jun/2025",
      "epsForecast": "$0.18",
      "noOfEsts": "3"
    },
    {
      "lastYearRptDt": "N/A",
      "lastYearEPS": "($0.07)",
      "time": "time-not-supplied",
      "symbol": "HIHO",
      "name": "Highway Holdings Limited",
      "marketCap": "$7,615,157",
      "fiscalQuarterEnding": "Mar/2025",
      "epsForecast": "",
      "noOfEsts": "9"
    }
  ]
}